openrecall/__init__.py
openrecall/app.py
OpenRecall-0.1.dist-info/LICENSE
OpenRecall-0.1.dist-info/METADATA
OpenRecall-0.1.dist-info/WHEEL
OpenRecall-0.1.dist-info/top_level.txt
OpenRecall-0.1.dist-info/RECORD
