Metadata-Version: 2.1
Name: OpenRecall
Version: 0.1
License-File: LICENSE
Requires-Dist: Flask ==3.0.3
Requires-Dist: numpy ==1.26.4
Requires-Dist: mss ==9.0.1
Requires-Dist: pillow ==10.3.0
Requires-Dist: sentence-transformers ==3.0.0
Requires-Dist: torch ==2.3.0
Requires-Dist: torchvision ==0.18.0
Requires-Dist: shapely
Requires-Dist: h5py
Requires-Dist: rapidfuzz
Requires-Dist: pyobjc
Provides-Extra: linux
Provides-Extra: macos
Requires-Dist: pyobjc ; extra == 'macos'
Provides-Extra: windows
Requires-Dist: pywin32 ; extra == 'windows'
